lightorm/__init__.py
lightorm/core.py
lightorm-0.0.7.dist-info/METADATA
lightorm-0.0.7.dist-info/WHEEL
lightorm-0.0.7.dist-info/top_level.txt
lightorm-0.0.7.dist-info/RECORD
