Metadata-Version: 2.1
Name: lightorm
Version: 0.0.7
Summary: Yet another, super lightweight MySQL ORM in Python.
Home-page: https://github.com/sabbiramin113008/tinyorm
Author: Sabbir Amin
Author-email: sabbiramin.cse11ruet@gmail.com
License: MIT
Keywords: python,Database,ORM,MySQL
Platform: UNKNOWN
Classifier: License :: OSI Approved :: MIT License
Classifier: Programming Language :: Python
Classifier: Operating System :: OS Independent
Classifier: Topic :: Utilities
Requires-Dist: pymysql
